{
    "code": [],
    "collection": [],
    "description": [],
    "distributorPartNumber": [],
    "eagleBoard": [
        "/Hardware/SparkFun_TRRS_3.5mm_Jack_Breakout.brd"
    ],
    "eagleSchem": [
        "/Hardware/SparkFun_TRRS_3.5mm_Jack_Breakout.sch"
    ],
    "footprintKicad": [],
    "footprintKicadDetails": [],
    "gitName": [
        "TRRS_3.5mm_Jack_Breakout"
    ],
    "gitRepo": [
        "https://github.com/sparkfun/TRRS_3.5mm_Jack_Breakout"
    ],
    "hexID": [
        "PRPR11570"
    ],
    "kicadBoard": [],
    "kicadSchem": [],
    "manufacturerPartNumber": [],
    "name": [
        "TRRS 3.5mm Jack Breakout"
    ],
    "oompColor": [
        "11570"
    ],
    "oompDesc": [
        "STAN"
    ],
    "oompID": [
        "PROJ-SPAR-11570-STAN-01"
    ],
    "oompIndex": [
        "01"
    ],
    "oompInstances": [],
    "oompParts": [
        {
            "JP1": "HEAD-I01-X-PI04-01",
            "JP2": "UNMATCHED-UNMATCHED-X-UNMATCHED-01"
        }
    ],
    "oompSize": [
        "SPAR"
    ],
    "oompType": [
        "PROJ"
    ],
    "oplPartNumber": [],
    "rawParts": [
        {
            "eagleBom": [
                {
                    "BOM": "",
                    "Description": "Schematic Frame",
                    "Device": "FRAME-LETTER",
                    "Package": "CREATIVE_COMMONS",
                    "Part": "FRAME1",
                    "Value": "FRAME-LETTER"
                },
                {
                    "BOM": "",
                    "Description": "Header 4",
                    "Device": "M04PTH",
                    "Package": "1X04",
                    "Part": "JP1",
                    "Value": ""
                },
                {
                    "BOM": "",
                    "Description": "Audio jack - 3.5mm TRRS variety - two rings.",
                    "Device": "AUDIO-JACK3",
                    "Package": "AUDIO-JACK-TRRS-SMD",
                    "Part": "JP2",
                    "Value": "AUDIO-JACK3"
                },
                {
                    "BOM": "",
                    "Description": "Spark Fun Electronics PCB Logo",
                    "Device": "LOGO-SFESK",
                    "Package": "SFE-LOGO-FLAME",
                    "Part": "JP3",
                    "Value": "LOGO-SFESK"
                },
                {
                    "BOM": "",
                    "Description": "Spark Fun Electronics PCB Logo",
                    "Device": "LOGO-SFESK",
                    "Package": "SFE-LOGO-FLAME",
                    "Part": "JP4",
                    "Value": "LOGO-SFESK"
                },
                {
                    "BOM": "",
                    "Description": "Open Source Hardware Logo This logo indicates the piece of hardware it is found on incorporates a OSHW license and/or adheres to the definition of open source hardware found here: http://freedomdefined.org/OSHW",
                    "Device": "OSHW-LOGOS",
                    "Package": "OSHW-LOGO-S",
                    "Part": "U$1",
                    "Value": "OSHW-LOGOS"
                }
            ],
            "kicadBom": []
        }
    ],
    "symbolKicad": [],
    "symbolKicadDetails": []
}